yamcs/cli/__main__.py
yamcs/cli/alarms.py
yamcs/cli/algorithms.py
yamcs/cli/bash_completion.sh
yamcs/cli/commands.py
yamcs/cli/completers.py
yamcs/cli/config.py
yamcs/cli/containers.py
yamcs/cli/dbshell.py
yamcs/cli/events.py
yamcs/cli/exceptions.py
yamcs/cli/instances.py
yamcs/cli/links.py
yamcs/cli/login.py
yamcs/cli/logout.py
yamcs/cli/packets.py
yamcs/cli/parameter_archive.py
yamcs/cli/parameters.py
yamcs/cli/processors.py
yamcs/cli/rocksdb.py
yamcs/cli/services.py
yamcs/cli/space_systems.py
yamcs/cli/storage.py
yamcs/cli/streams.py
yamcs/cli/tables.py
yamcs/cli/utils.py
yamcs/cli/protobuf/activities_pb2.py
yamcs/cli/protobuf/cmdhistory_pb2.py
yamcs/cli/protobuf/db_pb2.py
yamcs/cli/protobuf/replication_pb2.py
yamcs/cli/protobuf/security_pb2.py
yamcs/cli/protobuf/tablespace_pb2.py
yamcs/cli/protobuf/timeline_pb2.py
yamcs_cli-1.4.15.dist-info/licenses/LICENSE
yamcs_cli-1.4.15.dist-info/METADATA
yamcs_cli-1.4.15.dist-info/WHEEL
yamcs_cli-1.4.15.dist-info/entry_points.txt
yamcs_cli-1.4.15.dist-info/top_level.txt
yamcs_cli-1.4.15.dist-info/RECORD
